jsonfriendly_redshift/__init__.py
jsonfriendly_redshift/dict_utils.py
jsonfriendly_redshift/handler.py
jsonfriendly_redshift/utils.py
jsonfriendly_redshift-1.0.1.dist-info/LICENSE
jsonfriendly_redshift-1.0.1.dist-info/METADATA
jsonfriendly_redshift-1.0.1.dist-info/WHEEL
jsonfriendly_redshift-1.0.1.dist-info/top_level.txt
jsonfriendly_redshift-1.0.1.dist-info/RECORD
