Metadata-Version: 2.1
Name: jsonfriendly-redshift
Version: 1.0.1
Summary: A high level Python wrapper using pandas. It is meant to provide a point-in-time json data handling for redshift load Job.
Home-page: https://github.com/mishraamrish/jsonfriendly_redshift
Author: Amrish Mishra
License: MIT License
Platform: UNKNOWN
Classifier: Development Status :: 5 - Production/Stable
Classifier: Intended Audience :: Developers
Classifier: Intended Audience :: Information Technology
Classifier: Intended Audience :: System Administrators
Classifier: Natural Language :: English
Classifier: License :: OSI Approved :: MIT License
Classifier: Programming Language :: Python :: 3.6
Classifier: Programming Language :: Python :: 3.7
Classifier: Programming Language :: Python :: 3.8
Requires-Dist: pandas (==1.1.0)
Requires-Dist: numpy (==1.19.1)
Requires-Dist: psycopg2
